helper/__init__.py
helper/markdown.py
pre_commit_hooks_changelog-0.1.4.dist-info/METADATA
pre_commit_hooks_changelog-0.1.4.dist-info/WHEEL
pre_commit_hooks_changelog-0.1.4.dist-info/entry_points.txt
pre_commit_hooks_changelog-0.1.4.dist-info/top_level.txt
pre_commit_hooks_changelog-0.1.4.dist-info/RECORD
