Metadata-Version: 2.1
Name: pre-commit-hooks-changelog
Version: 0.1.4
Summary: generate Changelog.md from yaml files in changelog folder
Home-page: https://https://github.com/chrysa/pre-commit-hooks-changelog
Author: Anthony Greau
Author-email: greau.anthony@gmail.com
License: UNKNOWN
Download-URL: https://github.com/chrysa/pre-commit-hooks-changelog/archive/v0.1.4.tar.gz
Keywords: pre-commit,changelog
Platform: UNKNOWN
Classifier: Development Status :: 4 - Beta
Classifier: License :: OSI Approved :: MIT License
Classifier: Programming Language :: Python :: 3
Classifier: Programming Language :: Python :: 3 :: Only
Classifier: Programming Language :: Python :: 3.6
Classifier: Programming Language :: Python :: 3.7
Classifier: Programming Language :: Python :: 3.8
Classifier: Programming Language :: Python :: Implementation :: PyPy
Requires-Python: >=3.6
Requires-Dist: ruamel.yaml (>=0.16.5)
Provides-Extra: pre_commit
Requires-Dist: PyYAML (==5.1.2) ; extra == 'pre_commit'
Requires-Dist: isort (==4.3.21) ; extra == 'pre_commit'
Requires-Dist: pipenv (==2018.11.26) ; extra == 'pre_commit'
Provides-Extra: push
Requires-Dist: twine ; extra == 'push'
Provides-Extra: tests
Requires-Dist: coverage ; extra == 'tests'
Requires-Dist: mock ; extra == 'tests'
Requires-Dist: pytest ; extra == 'tests'
Requires-Dist: pytest-env ; extra == 'tests'
Requires-Dist: tox ; extra == 'tests'
